src/__init__.py
src/cli.py
src/model/__init__.py
src/model/directory_path.py
src/model/file_path.py
src/service/__init__.py
src/service/image_path_service.py
src/service/markdown_file_service.py
src/service/markdown_text_service.py
src/service/s3_service.py
test/__init__.py
test/test_image_path_service.py
test/test_markdown_service.py
test/test_open_markdown.py
markdown_hiko-0.2.3.dist-info/METADATA
markdown_hiko-0.2.3.dist-info/WHEEL
markdown_hiko-0.2.3.dist-info/entry_points.txt
markdown_hiko-0.2.3.dist-info/top_level.txt
markdown_hiko-0.2.3.dist-info/RECORD
