Metadata-Version: 2.1
Name: markdown-hiko
Version: 0.2.3
Summary: [Mardown Hiko] is a cli that uploads Markdown images to AWS S3.
Home-page: https://github.com/yutaka0m/markdown-hiko
Author: @yutaka0m
Author-email: UNKNOWN
License: MIT
Platform: UNKNOWN
Classifier: Programming Language :: Python :: 3.7
Classifier: Programming Language :: Python :: 3.8
Classifier: License :: OSI Approved :: MIT License
Requires-Dist: boto3 (==1.12.22)
Requires-Dist: botocore (==1.15.22)
